intelligent_pigeon-1.6.data/data/yolov4-custom.cfg
intelligent_pigeon-1.6.data/scripts/pigeon
pigeon/__init__.py
pigeon/pigeon.py
intelligent_pigeon-1.6.dist-info/METADATA
intelligent_pigeon-1.6.dist-info/WHEEL
intelligent_pigeon-1.6.dist-info/top_level.txt
intelligent_pigeon-1.6.dist-info/RECORD
