Metadata-Version: 2.1
Name: intelligent-pigeon
Version: 1.6
Summary: Intelligent Pigeon is a program made for IOT, by which you can detect Object from a Image and send to a server
Home-page: https://github.com/ujjwalkar0/intelligent_pigeon
Author: Ujjwal Kar
Author-email: ujjwalkar21@gmail.com
License: UNKNOWN
Keywords: YoLo,Object Detector,Artificial Intelligence,Internet of Things
Platform: UNKNOWN
Classifier: Programming Language :: Python :: 3
Classifier: Operating System :: Unix
Classifier: Operating System :: MacOS :: MacOS X
Requires-Python: >=3.6
Requires-Dist: Pillow (==8.4.0)
Requires-Dist: certifi (==2021.10.8)
Requires-Dist: charset-normalizer (==2.0.9)
Requires-Dist: idna (==3.3)
Requires-Dist: numpy (==1.21.4)
Requires-Dist: object-detector (==1.4)
Requires-Dist: opencv-python (==4.5.4.60)
Requires-Dist: requests (==2.26.0)
Requires-Dist: urllib3 (==1.26.7)
